README.md
emili.py
execute_send_email.py
reportrun
setup.py
emili.egg-info/PKG-INFO
emili.egg-info/SOURCES.txt
emili.egg-info/dependency_links.txt
emili.egg-info/requires.txt
emili.egg-info/top_level.txt